__init__.py
check.py
bluefin_rfq_client/__init__.py
bluefin_rfq_client/contracts.py
bluefin_rfq_client/quote.py
bluefin_rfq_client/rfq.py
bluefin_v2_client/__init__.py
bluefin_v2_client/api_service.py
bluefin_v2_client/client.py
bluefin_v2_client/constants.py
bluefin_v2_client/contracts.py
bluefin_v2_client/enumerations.py
bluefin_v2_client/interfaces.py
bluefin_v2_client/onboarding_signer.py
bluefin_v2_client/order_signer.py
bluefin_v2_client/socket_manager.py
bluefin_v2_client/sockets_lib.py
bluefin_v2_client/websocket_client.py
bluefin_v2_client_sui-1.2.0.dist-info/licenses/LICENSE
sui_utils/__init__.py
sui_utils/account.py
sui_utils/bcs.py
sui_utils/coin_utils.py
sui_utils/enumerations.py
sui_utils/rpc.py
sui_utils/signer.py
sui_utils/sui_interfaces.py
sui_utils/utilities.py
bluefin_v2_client_sui-1.2.0.dist-info/METADATA
bluefin_v2_client_sui-1.2.0.dist-info/WHEEL
bluefin_v2_client_sui-1.2.0.dist-info/top_level.txt
bluefin_v2_client_sui-1.2.0.dist-info/RECORD
